libname/__init__.py
libname/hello.py
myTestOnlyHello-0.0.1.dist-info/METADATA
myTestOnlyHello-0.0.1.dist-info/WHEEL
myTestOnlyHello-0.0.1.dist-info/top_level.txt
myTestOnlyHello-0.0.1.dist-info/RECORD
